<?xml version="1.0" encoding="UTF-8"?>
<krpano version="1.19"
        onstart="startup"
        logkey="false"
        bgcolor="#ffffff"
        projectfloorplanurl=""
        projecttitleid="project_title"
        projectdescriptionid="">


  <security cors="">
    <!--
    <crossdomainxml url="http://RESSOURCES_URL/crossdomain.xml" />
    -->
    <allowdomain domain="*" />
  </security>

  <krpano tour_firststartactiondone="false" tour_firstlittleplanet="true"/>
  <events name="startbehavioursevents" onxmlcomplete="startbehavioursxmlcompleteaction();" onloadcomplete="startLittlePlanetIntroEffect();" keep="true"/>

  <!-- generated by Panotour Pro V2.5.5 64bits : 07-12-2016 12-37-06 -->
  <!-- Plugins and Spot Styles -->
  <include url="%FIRSTXML%/StVal_skin.xml"/>
  <!-- Core actions -->
  <include url="%FIRSTXML%/StVal_core.xml"/>
  <!-- Tour Messages -->
  <include url="%FIRSTXML%/StVal_messages_fr.xml"/>

  <action name="startup">

    if (s !== null, if (startscene === null, set(startscene, get(s));); );
    if (startscene === null,
      set(startscene, pano10);
    );
    mainloadsceneStartup(get(startscene));
    if (h !== null,
      if (v !== null,
        if (f !== null,
          lookat(get(h), get(v), get(f));
         ,
          lookat(get(h), get(v));
        );
      ,
        if (f !== null,
          lookat(get(h), get(view.vlookat), get(f));
         ,
          lookat(get(h), get(view.vlookat));
        );
      );
    ,
      if (v !== null,
        if (f !== null,
          lookat(get(view.hlookat), get(v), get(f));
         ,
          lookat(get(view.hlookat), get(v));
        );
      ,
        if (f !== null,
          lookat(get(view.hlookat), get(view.vlookat), get(f));
        );
      );
    );
  </action>

  <!-- 2 Groups -->

  <!-- Group Groupe 11 : 1 panoramas -->
  

<!-- **** @PanoName="P_20161109_123800_PN" @PanoFile="/Users/vincentpochon/Desktop/ProjetStVal/stvalsources/P_20161109_123800_PN.jpg" **** -->
<!-- **** Width="9600px" Height="896px" **** -->
<scene name="pano10"
       heading="0"
       thumburl="%FIRSTXML%/p_20161109_123800_pn_10/thumbnail.jpg"
       backgroundsound=""
       backgroundsoundloops="0"
       haspolygons="false"
       titleid="pano10_title"
       descriptionid=""
       multires="true"
       planar="false"
       full360="false"
       video="false"
       seen="false">

    <autorotate horizon="0.000000" tofov="33.600000" waittime="1" speed="5"/>


    <panoview h="0.000000" v="0.000000" fov="33.600000" hmin="-180" hmax="180" vmin="-16.800000000000001" vmax="16.800000000000001" fovmax="90" />

    <view fisheye="0"
          limitview="range"
          hlookatmin="-180"
          hlookatmax="180"
          vlookatmin="-16.800000000000001"
          vlookatmax="16.800000000000001"
          maxpixelzoom="1.0"
          fovtype="VFOV"
          fovmax="90"
          fov="33.600000"
          hlookat="0.000000"
          vlookat="0.000000"/>

    <preview url="%FIRSTXML%/p_20161109_123800_pn_10/preview.jpg" type="CUBESTRIP" striporder="FRBLUD" />


        <image type="SPHERE" hfov="360" vfov="33.600000000000001" voffset="0" multires="true" baseindex="0" tilesize="512" devices="flash.and.desktop">
          <level tiledimagewidth="9600" tiledimageheight="895">
            <sphere url="p_20161109_123800_pn_10/0/%v_%u.jpg"/>
          </level>
        </image>
  
  <image type="CUBE" devices="desktop.and.html5">
    <front url="p_20161109_123800_pn_10/html5/0.jpg"/>
    <right url="p_20161109_123800_pn_10/html5/1.jpg"/>
    <back  url="p_20161109_123800_pn_10/html5/2.jpg"/>
    <left  url="p_20161109_123800_pn_10/html5/3.jpg"/>
    <up    url="p_20161109_123800_pn_10/html5/4.jpg"/>
    <down  url="p_20161109_123800_pn_10/html5/5.jpg"/>
  </image>
  
      <image type="CUBE" devices="tablet">
        <front url="p_20161109_123800_pn_10/tablet/0.jpg"/>
        <right url="p_20161109_123800_pn_10/tablet/1.jpg"/>
        <back  url="p_20161109_123800_pn_10/tablet/2.jpg"/>
        <left  url="p_20161109_123800_pn_10/tablet/3.jpg"/>
        <up    url="p_20161109_123800_pn_10/tablet/4.jpg"/>
        <down  url="p_20161109_123800_pn_10/tablet/5.jpg"/>
      </image>
      <image type="CUBE" devices="mobile">
        <front url="p_20161109_123800_pn_10/mobile/0.jpg"/>
        <right url="p_20161109_123800_pn_10/mobile/1.jpg"/>
        <back  url="p_20161109_123800_pn_10/mobile/2.jpg"/>
        <left  url="p_20161109_123800_pn_10/mobile/3.jpg"/>
        <up    url="p_20161109_123800_pn_10/mobile/4.jpg"/>
        <down  url="p_20161109_123800_pn_10/mobile/5.jpg"/>
      </image>






  <!-- **** 1 Point Spots **** -->



  <hotspot name="spotpoint53"
           ath="-7.810993" atv="5.835789"
           style="IconDefaultPointSpotStyle1"
           tag="point"
           descriptionid=""
           onclick="onclickspotpoint53"
           />
  <hotspot name="spotpoint53" devices="flash" zorder="3"/>
  <hotspot name="spotpoint53" devices="html5" zorder="3" zorder2="1"/>
  <action name="onclickspotpoint53">
  
        mainloadscene(pano51);lookat(get(panoview.h), get(panoview.v), get(panoview.fov));


  </action>



  <action name="hidepanopointspots">
    set(hotspot[spotpoint53].visible, false);
  </action>
  <action name="showpanopointspots">
    set(hotspot[spotpoint53].visible, true);
  </action>
  <events name="pano10stopanimatedspots" onremovepano="" />


  <action name="showpanospotsaction">
    if (tour_displayspots,
    showpanopointspots();




    );
  </action>
  <action name="hidepanospotsaction">
    hidepanopointspots();




  </action>


  <action name="setzorder2onstandardspots">
    if (device.html5,
      ifnot (device.desktop,


        set(hotspot[spotpoint53].zorder2, %1);

      );
    );
  </action>


</scene>


  <!-- Group Groupe 52 : 1 panoramas -->
  

<!-- **** @PanoName="IMG_0267" @PanoFile="/Users/vincentpochon/Desktop/ProjetStVal/stvalsources/IMG_0267.JPG" **** -->
<!-- **** Width="16382px" Height="3628px" **** -->
<scene name="pano51"
       heading="0"
       thumburl="%FIRSTXML%/img_0267_51/thumbnail.jpg"
       backgroundsound=""
       backgroundsoundloops="0"
       haspolygons="false"
       titleid="pano51_title"
       descriptionid=""
       multires="true"
       planar="false"
       full360="false"
       video="false"
       seen="false">

    <autorotate horizon="0.000000" tofov="0.221463" waittime="1" speed="5"/>


    <panoview h="0.000000" v="0.000000" fov="0.221463" hmin="-90.280000000000001" hmax="90.280000000000001" vmin="-19.969160156250002" vmax="19.969160156250002" fovmax="79.726500000000001" />

    <view fisheye="0"
          limitview="range"
          hlookatmin="-90.280000000000001"
          hlookatmax="90.280000000000001"
          vlookatmin="-19.969160156250002"
          vlookatmax="19.969160156250002"
          maxpixelzoom="1.0"
          fovtype="VFOV"
          fovmax="79.726500000000001"
          fov="0.221463"
          hlookat="0.000000"
          vlookat="0.000000"/>

    <preview url="%FIRSTXML%/img_0267_51/preview.jpg" type="CUBESTRIP" striporder="FRBLUD" />


        <image type="SPHERE" hfov="180.56" vfov="39.938320312500004" voffset="0" multires="true" baseindex="0" tilesize="512" devices="flash.and.desktop">
          <level tiledimagewidth="16382" tiledimageheight="3628">
            <sphere url="img_0267_51/2/%v_%u.jpg"/>
          </level>
          <level tiledimagewidth="8191" tiledimageheight="1814">
            <sphere url="img_0267_51/1/%v_%u.jpg"/>
          </level>
          <level tiledimagewidth="4095" tiledimageheight="907">
            <sphere url="img_0267_51/0/%v_%u.jpg"/>
          </level>
        </image>
  
  <image type="CUBE" devices="desktop.and.html5">
    <front url="img_0267_51/html5/0.jpg"/>
    <right url="img_0267_51/html5/1.jpg"/>
    <back  url="img_0267_51/html5/2.jpg"/>
    <left  url="img_0267_51/html5/3.jpg"/>
    <up    url="img_0267_51/html5/4.jpg"/>
    <down  url="img_0267_51/html5/5.jpg"/>
  </image>
  
      <image type="CUBE" devices="tablet">
        <front url="img_0267_51/tablet/0.jpg"/>
        <right url="img_0267_51/tablet/1.jpg"/>
        <back  url="img_0267_51/tablet/2.jpg"/>
        <left  url="img_0267_51/tablet/3.jpg"/>
        <up    url="img_0267_51/tablet/4.jpg"/>
        <down  url="img_0267_51/tablet/5.jpg"/>
      </image>
      <image type="CUBE" devices="mobile">
        <front url="img_0267_51/mobile/0.jpg"/>
        <right url="img_0267_51/mobile/1.jpg"/>
        <back  url="img_0267_51/mobile/2.jpg"/>
        <left  url="img_0267_51/mobile/3.jpg"/>
        <up    url="img_0267_51/mobile/4.jpg"/>
        <down  url="img_0267_51/mobile/5.jpg"/>
      </image>







  <action name="setzorder2onstandardspots">
    if (device.html5,
      ifnot (device.desktop,


      );
    );
  </action>


</scene>


  <krpano nofullspherepanoavailable="true" />



</krpano>

